std_py_logger/__init__.py
std_py_logger/std_logger.py
std_py_logger-0.0.6.dist-info/METADATA
std_py_logger-0.0.6.dist-info/WHEEL
std_py_logger-0.0.6.dist-info/licenses/LICENSE
std_py_logger-0.0.6.dist-info/RECORD
