Metadata-Version: 2.4
Name: std-py-logger
Version: 0.0.6
Summary: A simple colored logger for Python
Project-URL: Homepage, https://github.com/gpastal24/std_py_logger
Project-URL: Bug Tracker, https://github.com/gpastal24/std_py_logger/issues
Author: gpastal
License-File: LICENSE
Classifier: License :: OSI Approved :: MIT License
Classifier: Operating System :: OS Independent
Classifier: Programming Language :: Python :: 3
Requires-Python: >=3.8
